diacamma/__init__.py
diacamma/condominium/__init__.py
diacamma/condominium/build
diacamma/condominium/editors.py
diacamma/condominium/models.py
diacamma/condominium/test_tools.py
diacamma/condominium/tests.py
diacamma/condominium/tests_callfunds.py
diacamma/condominium/tests_expense.py
diacamma/condominium/views.py
diacamma/condominium/views_callfunds.py
diacamma/condominium/views_classload.py
diacamma/condominium/views_expense.py
diacamma/condominium/views_report.py
diacamma/condominium/docs/build_en/doctrees/call_of_funds.doctree
diacamma/condominium/docs/build_en/doctrees/classloads.doctree
diacamma/condominium/docs/build_en/doctrees/environment.pickle
diacamma/condominium/docs/build_en/doctrees/expense.doctree
diacamma/condominium/docs/build_en/doctrees/index.doctree
diacamma/condominium/docs/build_en/doctrees/owners.doctree
diacamma/condominium/docs/build_en/doctrees/payoff.doctree
diacamma/condominium/docs/build_en/doctrees/report.doctree
diacamma/condominium/docs/build_fr/doctrees/account_contraints.doctree
diacamma/condominium/docs/build_fr/doctrees/call_of_funds.doctree
diacamma/condominium/docs/build_fr/doctrees/classloads.doctree
diacamma/condominium/docs/build_fr/doctrees/environment.pickle
diacamma/condominium/docs/build_fr/doctrees/expense.doctree
diacamma/condominium/docs/build_fr/doctrees/index.doctree
diacamma/condominium/docs/build_fr/doctrees/owners.doctree
diacamma/condominium/docs/build_fr/doctrees/payoff.doctree
diacamma/condominium/docs/build_fr/doctrees/report.doctree
diacamma/condominium/docs/en/Makefile
diacamma/condominium/docs/en/call_of_funds.png
diacamma/condominium/docs/en/call_of_funds.rst
diacamma/condominium/docs/en/classloads.rst
diacamma/condominium/docs/en/conf.py
diacamma/condominium/docs/en/expense.png
diacamma/condominium/docs/en/expense.rst
diacamma/condominium/docs/en/index.rst
diacamma/condominium/docs/en/owners.rst
diacamma/condominium/docs/en/payoff.png
diacamma/condominium/docs/en/payoff.rst
diacamma_syndic-2.7.5.25070818.dist-info/licenses/LICENSE
diacamma_syndic-2.7.5.25070818.dist-info/METADATA
diacamma_syndic-2.7.5.25070818.dist-info/WHEEL
diacamma_syndic-2.7.5.25070818.dist-info/top_level.txt
diacamma_syndic-2.7.5.25070818.dist-info/RECORD
